LICENSE.md
README.md
pyproject.toml
src/mlx_textgen/__init__.py
src/mlx_textgen/cache_utils.py
src/mlx_textgen/chat_presets.py
src/mlx_textgen/chat_utils.py
src/mlx_textgen/cli.py
src/mlx_textgen/engine.py
src/mlx_textgen/generation_utils.py
src/mlx_textgen/log_utils.py
src/mlx_textgen/model_utils.py
src/mlx_textgen/rotating_kv_cache_patch.py
src/mlx_textgen/sampling_utils.py
src/mlx_textgen/server.py
src/mlx_textgen/tokenizer_utils.py
src/mlx_textgen/utils.py
src/mlx_textgen.egg-info/PKG-INFO
src/mlx_textgen.egg-info/SOURCES.txt
src/mlx_textgen.egg-info/dependency_links.txt
src/mlx_textgen.egg-info/entry_points.txt
src/mlx_textgen.egg-info/requires.txt
src/mlx_textgen.egg-info/top_level.txt