Metadata-Version: 2.4
Name: mlx-textgen
Version: 0.2.0
Summary: An OpenAI-compatible API LLM engine with smart prompt caching, batch processing, structured output with guided decoding, and function calling for all models using MLX.
Author-email: Nathan Tam <nathan1295@gmail.com>
License: MIT
Project-URL: Homepage, https://github.com/nath1295/MLX-Textgen
Classifier: Programming Language :: Python :: 3
Classifier: License :: OSI Approved :: MIT License
Classifier: Operating System :: MacOS :: MacOS X
Requires-Python: >=3.9
License-File: LICENSE.md
Requires-Dist: mlx-lm>=0.24.0
Requires-Dist: mlx-vlm>=0.1.26
Requires-Dist: outlines>=0.2.3
Requires-Dist: fastapi
Requires-Dist: uvicorn
Dynamic: license-file
